Metadata-Version: 2.1
Name: craftdot
Version: 0.0.3
Summary: easily to make pretty graphviz diagram
Home-page: https://github.com/kaleocheng/craftdot
Author: Kaleo Cheng
Author-email: kaleocheng@gmail.com
License: UNKNOWN
Platform: UNKNOWN
Classifier: Programming Language :: Python :: 3
Classifier: License :: OSI Approved :: MIT License
Classifier: Operating System :: OS Independent
